client/__init__.py
client/client.py
client/client_file/__init__.py
client/client_file/add_contact.py
client/client_file/client_database.py
client/client_file/del_contact.py
client/client_file/main_window.py
client/client_file/main_window_conv.py
client/client_file/transp.py
client/client_file/user_name_dialog.py
client/common/__init__.py
client/common/decos.py
client/common/descrptrs.py
client/common/errors.py
client/common/metaclasses.py
client/common/utils.py
client/common/variables.py
client/logs/__init__.py
client/logs/config_client_log.py
client/logs/config_server_log.py
Singularity_client-0.0.2.dist-info/METADATA
Singularity_client-0.0.2.dist-info/WHEEL
Singularity_client-0.0.2.dist-info/top_level.txt
Singularity_client-0.0.2.dist-info/RECORD
